thunderboltz/__init__.py
thunderboltz/cpp/Collision.cpp
thunderboltz/cpp/DSMC0D.cpp
thunderboltz/cpp/DSMC0D.h
thunderboltz/cpp/Parser.cpp
thunderboltz/data/CCC/He_DCS_potl.csv
thunderboltz/data/CCC/He_DCS_tcs.csv
thunderboltz/data/CCC/He_thresholds.csv
thunderboltz/data/Ralchenko_He_CS.csv
thunderboltz/data/citations.txt
thunderboltz/input.py
thunderboltz/kinetic.py
thunderboltz/parallel.py
thunderboltz/parameters.py
thunderboltz/parsing.py
thunderboltz/plotting/figure_gen.py
thunderboltz/plotting/pdplot.py
thunderboltz/plotting/styles.py
thunderboltz/tb.py
thunderboltz-0.4.4.dist-info/LICENSE
thunderboltz-0.4.4.dist-info/METADATA
thunderboltz-0.4.4.dist-info/WHEEL
thunderboltz-0.4.4.dist-info/RECORD
