Metadata-Version: 2.3
Name: thunderboltz
Version: 0.4.4
Summary: A 0D Direct Simulation Monte-Carlo code for the calculation of transport coefficients and 0D gas modeling.
License: GPL-3.0-or-later
Author: Ryan Park
Author-email: rmpark@umich.edu
Requires-Python: >=3.8
Classifier: License :: OSI Approved :: GNU General Public License v3 or later (GPLv3+)
Classifier: Programming Language :: Python :: 3
Classifier: Programming Language :: Python :: 3.8
Classifier: Programming Language :: Python :: 3.9
Classifier: Programming Language :: Python :: 3.10
Classifier: Programming Language :: Python :: 3.11
Classifier: Programming Language :: Python :: 3.12
Classifier: Programming Language :: Python :: 3.13
Requires-Dist: matplotlib (>=3.7.1,<=3.9)
Requires-Dist: numpy (>=1.23.0,<=1.27.0)
Requires-Dist: pandas (>=2.0.1)
Requires-Dist: scipy (>=1.7.3) ; python_version >= "3.8" and python_version < "3.13"
Requires-Dist: seaborn (>=0.12.2)
